Memory64/Bin32.py
Memory64/D3Gui.py
Memory64/Function.py
Memory64/Memo.py
Memory64/ModLib.py
Memory64/Struct.py
Memory64/__init__.py
Memory64/Libs/Bin32.dll
Memory64/const/__init__.py
Memory64-1.0.3.dev2.dist-info/LICENSE
Memory64-1.0.3.dev2.dist-info/METADATA
Memory64-1.0.3.dev2.dist-info/WHEEL
Memory64-1.0.3.dev2.dist-info/top_level.txt
Memory64-1.0.3.dev2.dist-info/RECORD
