Metadata-Version: 2.1
Name: Memory64
Version: 1.0.3.dev2
Summary: 一个内存读写模块, 今后会更加的完善, 在此非常感谢大家的支持 !
Home-page: https://space.bilibili.com/84500837
Author: 忆梦
Author-email: 2872930558@qq.com
License: UNKNOWN
Platform: UNKNOWN
License-File: LICENSE
